CHANGES.txt
LICENSE.html
MANIFEST.in
README.rst
setup.py
storm/DistributedRPC.py
storm/DistributedRPCInvocations.py
storm/Nimbus.py
storm/__init__.py
storm/constants.py
storm/drpc.py
storm/ttypes.py
storm_drpc_client.egg-info/PKG-INFO
storm_drpc_client.egg-info/SOURCES.txt
storm_drpc_client.egg-info/dependency_links.txt
storm_drpc_client.egg-info/requires.txt
storm_drpc_client.egg-info/top_level.txt
storm_drpc_client.egg-info/zip-safe