Metadata-Version: 1.0
Name: storm-drpc-client
Version: 0.1.1
Summary: Simple pythonic interface around thrift-generated DRPC client.
Home-page: https://github.com/strongh/storm-drpc-client-py
Author: Homer Strong
Author-email: homer.strong@gmail.com
License: LICENSE.html
Platform: any
